<?xml version="1.0" encoding="utf-8"?>
<!DOCTYPE hibernate-mapping PUBLIC "-//Hibernate/Hibernate Mapping DTD 3.0//EN"
"http://hibernate.sourceforge.net/hibernate-mapping-3.0.dtd">
<!-- 
    Mapping file autogenerated by MyEclipse Persistence Tools
-->
<hibernate-mapping>
    <class name="scu.nine.modle.UserInfo" table="user_info" catalog="film">
        <id name="userId" type="java.lang.Integer">
            <column name="user_id" />
            <generator class="native" />
        </id>
        <property name="userName" type="java.lang.String">
            <column name="user_name" length="30" not-null="true" />
        </property>
        <property name="userPassword" type="java.lang.String">
            <column name="user_password" length="30" not-null="true" />
        </property>
        <property name="userRealname" type="java.lang.String">
            <column name="user_realname" length="20" />
        </property>
        <property name="userSex" type="java.lang.Integer">
            <column name="user_sex" />
        </property>
        <property name="userIdcard" type="java.lang.String">
            <column name="user_idcard" length="20" not-null="true" />
        </property>
        <property name="userBirth" type="java.util.Date">
            <column name="user_birth" length="0" />
        </property>
        <property name="userMarry" type="java.lang.Integer">
            <column name="user_marry" />
        </property>
        <property name="userCity" type="java.lang.String">
            <column name="user_city" length="50" />
        </property>
        <property name="userAddress" type="java.lang.String">
            <column name="user_address" length="200" />
        </property>
        <property name="userPostcode" type="java.lang.String">
            <column name="user_postcode" length="10" />
        </property>
        <property name="userPnumber" type="java.lang.String">
            <column name="user_pnumber" length="15" not-null="true" />
        </property>
        <property name="userEmail" type="java.lang.String">
            <column name="user_email" length="40" not-null="true" />
        </property>
        <set name="payInfos" inverse="true">
            <key>
                <column name="user_id" not-null="true" />
            </key>
            <one-to-many class="scu.nine.modle.PayInfo" />
        </set>
        <set name="newsViewInfos" inverse="true">
            <key>
                <column name="user_id" />
            </key>
            <one-to-many class="scu.nine.modle.NewsViewInfo" />
        </set>
        <set name="messageInfos" inverse="true">
            <key>
                <column name="user_id" />
            </key>
            <one-to-many class="scu.nine.modle.MessageInfo" />
        </set>
        <set name="movieViewInfos" inverse="true">
            <key>
                <column name="user_id" not-null="true" />
            </key>
            <one-to-many class="scu.nine.modle.MovieViewInfo" />
        </set>
    </class>
</hibernate-mapping>
